breedgym/__init__.py
breedgym/breedgym.py
breedgym/wrappers.py
breedgym/data/small_geno.npy
breedgym/utils/__init__.py
breedgym/utils/index_functions.py
breedgym/utils/paths.py
breedgym/utils/plot_utils.py
breedgym/vector/__init__.py
breedgym/vector/breeding_programs_env.py
breedgym/vector/vec_env.py
breedgym/vector/vec_wrappers.py
breedgym-0.0.2a0.dist-info/LICENSE
breedgym-0.0.2a0.dist-info/METADATA
breedgym-0.0.2a0.dist-info/WHEEL
breedgym-0.0.2a0.dist-info/top_level.txt
breedgym-0.0.2a0.dist-info/RECORD
