Metadata-Version: 2.1
Name: breedgym
Version: 0.0.2a0
Summary: Suite of Gymnasium environments for optimizing breeding programs
Author-email: "Omar G. Younis" <omar.g.younis@gmail.com>
License: BSD-3-Clause
Project-URL: Repository, https://github.com/younik/breedgym
Project-URL: Bug Report, https://github.com/younik/breedgym/issues
Keywords: Reinforcement Learning,Breeding,genetics,bioinformatics
Classifier: Development Status :: 4 - Beta
Classifier: Programming Language :: Python :: 3
Classifier: Programming Language :: Python :: 3.9
Classifier: Programming Language :: Python :: 3.10
Classifier: Programming Language :: Python :: 3.11
Classifier: Programming Language :: Python :: 3.12
Classifier: Intended Audience :: Science/Research
Requires-Python: >=3.9
License-File: LICENSE
Requires-Dist: numpy
Requires-Dist: pandas
Requires-Dist: matplotlib
Requires-Dist: chromax
Requires-Dist: gymnasium >=0.29
Requires-Dist: jax
Requires-Dist: jaxtyping
Provides-Extra: docs
Requires-Dist: sphinx-rtd-theme ; extra == 'docs'
Provides-Extra: testing
Requires-Dist: pytest ; extra == 'testing'
